Metadata-Version: 2.1
Name: zhanlan1
Version: 0.1.0
Summary: Special package
Home-page: https://github.com/liujiang9/Utils
Author: Adyan
Author-email: 228923910@qq.com
License: UNKNOWN
Platform: UNKNOWN
Classifier: Programming Language :: Python :: 3
Classifier: License :: OSI Approved :: MIT License
Classifier: Operating System :: OS Independent
Requires-Python: >=3.7
License-File: LICENSE
